Metadata-Version: 2.4
Name: mseep-agentic-radar
Version: 0.13.1
Summary: A python library for generating reports for agentic systems.
Author-email: mseep <support@skydeck.ai>
Maintainer-email: SPLX <developers@splx.ai>
License:                                  Apache License
Project-URL: Homepage, https://github.com/splx-ai/agentic-radar
Project-URL: Source, https://github.com/splx-ai/agentic-radar
Project-URL: Tracker, https://github.com/splx-ai/agentic-radar/issues
Classifier: Development Status :: 3 - Alpha
Classifier: License :: OSI Approved :: Apache Software License
Classifier: Programming Language :: Python :: 3
Classifier: Programming Language :: Python :: 3.9
Requires-Python: >=3.9
License-File: LICENSE
Requires-Dist: pydantic>=2.10.6
Requires-Dist: typer-slim>=0.15.1
Requires-Dist: jinja2<4.0.0,>=3.1.5
Requires-Dist: importlib-resources<7.0.0,>=6.5.2
Requires-Dist: openai<2.0.0,>=1.73.0
Requires-Dist: dotenv<0.10.0,>=0.9.9
Requires-Dist: rich<14.0.0,>=13.7.0
Requires-Dist: pyyaml<7.0.0,>=6.0.2
Provides-Extra: crewai
Requires-Dist: crewai-tools>=0.38.1; (python_version >= "3.10" and python_version < "3.13") and extra == "crewai"
Provides-Extra: openai-agents
Requires-Dist: openai-agents<0.0.14,>=0.0.13; extra == "openai-agents"
Dynamic: license-file
